[
  {
    "vn": "họ ủng hộ tôi nên hộ giúp đỡ tôi",
    "en": "They support me so they help me",
    "zh": "他們支持我，所以他們幫助我"
  },
  {
    "vn": "tôi uống cà phê trước khi đi ngủ",
    "en": "I drink coffee before going to bed",
    "zh": "我在睡覺前喝咖啡"
  },
  {
    "vn": "cả mèo và chó đều thích thịt",
    "en": "Both cats and dogs like meat",
    "zh": "貓和狗都喜歡肉"
  },
  {
    "vn": "Đứa trẻ không ăn mà cũng không uống",
    "en": "The child neither eats nor drinks",
    "zh": "孩子既不吃也不喝"
  },
  {
    "vn": "Cô ấy không những hát mà còn nhảy",
    "en": "She not only sings but also dances",
    "zh": "她不僅唱歌而且跳舞"
  },
  {
    "vn": "Tuy cô ấy thích cái váy nhưng cô ấy không mua nó",
    "en": "Although she likes the dress, she doesn't buy it",
    "zh": "雖然她喜歡這條裙子，但她沒有買"
  },
  {
    "vn": "Hò mua không những máy tính mà còn điện thoại",
    "en": "He buys not only a computer but also a phone",
    "zh": "他買的不僅是電腦，還有手機"
  },
  {
    "vn": "nếu bạn hát thì cô ấy múa",
    "en": "If you sing, she dances",
    "zh": "如果你唱歌，她就跳舞"
  },
  {
    "vn": "Người đàn ông nói cả tiếng Việt và tiếng Anh.",
    "en": "This person speaks both Vietnamese and English.",
    "zh": "這個人會說越南語和英語。"
  },
  {
    "vn": "Học sinh của chúng tôi đều biết tiếng Anh.",
    "en": "Our students all know English.",
    "zh": "我們的學生都知道英語。"
  },
  {
    "vn": "Chúng tôi không có giường để ngủ",
    "en": "We don't have a bed to sleep",
    "zh": "我們沒有床可以睡覺"
  },
  {
    "vn": "Chúng tôi nơi tạm biệt trước khi đi Việt Nam",
    "en": "We say goodbye before going to Vietnam",
    "zh": "我們在去越南之前說再見"
  },
  {
    "vn": "Tôi hỏi nhưng anh ấy không trả lời.",
    "en": "I asked but he didn't answer.",
    "zh": "我問了，但他沒有回答。"
  },
  {
    "vn": "Chúng tôi muốn có một con vịt nên chúng tôi mua một con vịt.",
    "en": "We want to have a duck, so we buy a duck.",
    "zh": "我們想要一隻鴨子，所以我們買了一隻鴨子。"
  },
  {
    "vn": "Tôi mua một cái máy tính hoặc một quyển sách",
    "en": "I buy a computer or a book",
    "zh": "我買一台電腦或一本書"
  },
  {
    "vn": "Anh ấy nói trong khi ngủ",
    "en": "He talks while sleeping",
    "zh": "他在睡覺時說話"
  },
  {
    "vn": "những giây phút đặc biệt",
    "en": "special moments",
    "zh": "特殊的時刻"
  },
  {
    "vn": "ngày cá tháng tư",
    "en": "April Fool's Day",
    "zh": "愚人節"
  },
  {
    "vn": "Yêu như không có ngày mai",
    "en": "Love like there's no tomorrow",
    "zh": "愛就像沒有明天"
  },
  {
    "vn": "Có bao nhiêu ngày trong một năm?",
    "en": "How many days are there in a year?",
    "zh": "一年有多少天？"
  }
]





